cool_pipe/__init__.py
cool_pipe/pipeline.py
cool_pipe-0.1.0.dist-info/LICENSE
cool_pipe-0.1.0.dist-info/METADATA
cool_pipe-0.1.0.dist-info/WHEEL
cool_pipe-0.1.0.dist-info/top_level.txt
cool_pipe-0.1.0.dist-info/RECORD
