Metadata-Version: 2.1
Name: cool-pipe
Version: 0.1.0
Summary: Simple pipelines for python functions and methods
Home-page: https://github.com/dailydaniel/cool_pipe
Author: Daniel Zholkovsky
Author-email: daniel@zholkovsky.com
Classifier: Programming Language :: Python :: 3
Classifier: License :: OSI Approved :: MIT License
Classifier: Operating System :: OS Independent
Requires-Python: >=3.6
License-File: LICENSE
